leversc/__init__.py
leversc/_property.py
leversc/_readImage.py
leversc/leversc.py
leversc/test.py
leversc/test_cells3d.py
leversc/test_leversc.py
leversc/test_random.py
leversc-22.1.261.dist-info/METADATA
leversc-22.1.261.dist-info/WHEEL
leversc-22.1.261.dist-info/top_level.txt
leversc-22.1.261.dist-info/RECORD
