Metadata-Version: 2.1
Name: leversc
Version: 22.1.261
Summary: 4-D scriptable visualization
Home-page: https://leverjs.net/leversc
Author: Andrew R. Cohen & Mark Winter
Author-email: andrew.r.cohen@drexel.edu
License: UNKNOWN
Platform: UNKNOWN
Classifier: Programming Language :: Python :: 3
Classifier: License :: OSI Approved :: MIT License
Classifier: Operating System :: OS Independent
Requires-Python: >=3.6
Requires-Dist: matplotlib
Requires-Dist: h5py
Requires-Dist: imageio
Requires-Dist: requests
Requires-Dist: scikit-image
Requires-Dist: pooch
